narca/__init__.py
narca/agent.py
narca/astar.py
narca/drunk_dwarf.py
narca/nar.py
narca/narsese.py
narca/udpnar.py
narca/utils.py
narca/zelda.py
narca-0.2.0.dist-info/LICENSE
narca-0.2.0.dist-info/WHEEL
narca-0.2.0.dist-info/METADATA
narca-0.2.0.dist-info/RECORD
